redis_msgpack/__init__.py
redis_msgpack/client.py
redis_msgpack/django_integration.py
redis_msgpack/utils.py
redis_msgpack-0.1.1.dist-info/LICENSE
redis_msgpack-0.1.1.dist-info/METADATA
redis_msgpack-0.1.1.dist-info/WHEEL
redis_msgpack-0.1.1.dist-info/RECORD
