Metadata-Version: 2.3
Name: redis-msgpack
Version: 0.1.1
Summary: Redis client with msgpack serialization
License: MIT
Keywords: redis,msgpack,cache,django
Author: krishnendu
Author-email: krishnenduchatterjee25@gmail.com
Requires-Python: >=3.12
Classifier: Development Status :: 4 - Beta
Classifier: Intended Audience :: Developers
Classifier: License :: OSI Approved :: MIT License
Classifier: Programming Language :: Python :: 3
Classifier: Programming Language :: Python :: 3.12
Classifier: Framework :: Django
Classifier: Topic :: Database
Classifier: Topic :: Software Development :: Libraries :: Python Modules
Provides-Extra: django
Requires-Dist: django (>=3.2) ; extra == "django"
Requires-Dist: msgpack (>=1.1.0,<2.0.0)
Requires-Dist: redis (>=5.2.1,<6.0.0)
Project-URL: Documentation, https://github.com/yourusername/redis-msgpack#readme
Project-URL: Homepage, https://github.com/yourusername/redis-msgpack
Project-URL: Repository, https://github.com/yourusername/redis-msgpack.git
